{
    "adult": false,
    "also_known_as": [
        "Owen William Teague",
        "Оуэн Тиг",
        "Оуен Вільям Тіг",
        "Овен Тіґ",
        "אוון טיג"
    ],
    "biography": "",
    "birthday": "1998-12-08",
    "deathday": null,
    "gender": 2,
    "homepage": null,
    "id": 1586047,
    "imdb_id": "nm4977122",
    "known_for_department": "Acting",
    "name": "오웬 티그",
    "place_of_birth": "Tampa, Florida, USA",
    "popularity": 39.447,
    "profile_path": "/tgCkGE0LIggyjMmgSwHhpZAkfJs.jpg"
}